pixiverse/__init__.py
pixiverse/pixiverse.py
pixiverse/utils.py
pixiverse-0.0.1.dist-info/licenses/LICENSE
pixiverse-0.0.1.dist-info/METADATA
pixiverse-0.0.1.dist-info/WHEEL
pixiverse-0.0.1.dist-info/top_level.txt
pixiverse-0.0.1.dist-info/RECORD
