Metadata-Version: 2.4
Name: pixiverse
Version: 0.0.1
Summary: 📸 Pixiverse: A lightweight, intuitive library for reading, processing, and saving images in all popular formats—effortlessly.
Author-email: spring <springnode@gmail.com>
License: MIT
Project-URL: Homepage, https://github.com/VisNViz/pixiverse
Project-URL: Issues, https://github.com/VisNViz/pixiverse/issues
Keywords: python,opencv,heif,heic,avif,pillow
Classifier: Development Status :: 2 - Pre-Alpha
Classifier: Programming Language :: Python :: 3
Classifier: Operating System :: OS Independent
Requires-Python: >=3.6
License-File: LICENSE
Requires-Dist: opencv-python
Requires-Dist: pillow
Requires-Dist: pillow_heif
Requires-Dist: pillow-avif-plugin
Dynamic: license-file
